strmprivacy/__init__.py
strmprivacy/api/__init__.py
strmprivacy/api/account/__init__.py
strmprivacy/api/account/v1/__init__.py
strmprivacy/api/account/v1/account_v1_pb2.py
strmprivacy/api/account/v1/account_v1_pb2_grpc.py
strmprivacy/api/agents/__init__.py
strmprivacy/api/agents/v1/__init__.py
strmprivacy/api/agents/v1/batch_exporters_agent_v1_pb2.py
strmprivacy/api/agents/v1/batch_exporters_agent_v1_pb2_grpc.py
strmprivacy/api/agents/v1/batch_jobs_agent_v1_pb2.py
strmprivacy/api/agents/v1/batch_jobs_agent_v1_pb2_grpc.py
strmprivacy/api/agents/v1/data_connector_agent_v1_pb2.py
strmprivacy/api/agents/v1/data_connector_agent_v1_pb2_grpc.py
strmprivacy/api/agents/v1/streams_agent_v1_pb2.py
strmprivacy/api/agents/v1/streams_agent_v1_pb2_grpc.py
strmprivacy/api/audit/__init__.py
strmprivacy/api/audit/v1/__init__.py
strmprivacy/api/audit/v1/audit_v1_pb2.py
strmprivacy/api/audit/v1/audit_v1_pb2_grpc.py
strmprivacy/api/batch_exporters/__init__.py
strmprivacy/api/batch_exporters/v1/__init__.py
strmprivacy/api/batch_exporters/v1/batch_exporters_v1_pb2.py
strmprivacy/api/batch_exporters/v1/batch_exporters_v1_pb2_grpc.py
strmprivacy/api/batch_jobs/__init__.py
strmprivacy/api/batch_jobs/v1/__init__.py
strmprivacy/api/batch_jobs/v1/batch_jobs_v1_pb2.py
strmprivacy/api/batch_jobs/v1/batch_jobs_v1_pb2_grpc.py
strmprivacy/api/categories/__init__.py
strmprivacy/api/categories/v1alpha/__init__.py
strmprivacy/api/categories/v1alpha/categories_v1alpha_pb2.py
strmprivacy/api/categories/v1alpha/categories_v1alpha_pb2_grpc.py
strmprivacy/api/cli/__init__.py
strmprivacy/api/cli/v1/__init__.py
strmprivacy/api/cli/v1/cli_pb2.py
strmprivacy/api/cli/v1/cli_pb2_grpc.py
strmprivacy/api/comments/__init__.py
strmprivacy/api/comments/v1/__init__.py
strmprivacy/api/comments/v1/comments_v1_pb2.py
strmprivacy/api/comments/v1/comments_v1_pb2_grpc.py
strmprivacy/api/credentials/__init__.py
strmprivacy/api/credentials/v1/__init__.py
strmprivacy/api/credentials/v1/credentials_v1_pb2.py
strmprivacy_api_definitions-3.18.4.dist-info/METADATA
strmprivacy_api_definitions-3.18.4.dist-info/WHEEL
strmprivacy_api_definitions-3.18.4.dist-info/top_level.txt
strmprivacy_api_definitions-3.18.4.dist-info/RECORD
