Metadata-Version: 2.1
Name: strmprivacy-api-definitions
Version: 3.18.4
Summary: STRM Privacy API definitions
Home-page: UNKNOWN
Author: Stream Machine B.V.
Author-email: apis@strmprivacy.io
License: UNKNOWN
Keywords: strmprivacy api definitions
Platform: UNKNOWN
Classifier: Programming Language :: Python :: 3.6
Classifier: Programming Language :: Python :: 3.7
Classifier: Programming Language :: Python :: 3.8
Classifier: Programming Language :: Python :: 3.9
Classifier: Intended Audience :: Developers
Classifier: Operating System :: OS Independent
Classifier: Topic :: Internet :: WWW/HTTP
Requires-Python: >=3.6
Requires-Dist: grpcio ==1.50.0
